jupyterhub_client/__init__.py
jupyterhub_client/async.py
jupyterhub_client/base.py
jupyterhub_client/sync.py
jupyterhub_client-0.1.0.dist-info/DESCRIPTION.rst
jupyterhub_client-0.1.0.dist-info/METADATA
jupyterhub_client-0.1.0.dist-info/RECORD
jupyterhub_client-0.1.0.dist-info/WHEEL
jupyterhub_client-0.1.0.dist-info/metadata.json
jupyterhub_client-0.1.0.dist-info/top_level.txt
